pyatsyn/__init__.py
pyatsyn/ats_io.py
pyatsyn/ats_structure.py
pyatsyn/ats_synth.py
pyatsyn/atsa/__init__.py
pyatsyn/atsa/critical_bands.py
pyatsyn/atsa/peak_detect.py
pyatsyn/atsa/peak_tracking.py
pyatsyn/atsa/residual.py
pyatsyn/atsa/tracker.py
pyatsyn/atsa/utils.py
pyatsyn/atsa/windows.py
pyatsyn-1.0.0.dist-info/LICENSE.rst
pyatsyn-1.0.0.dist-info/METADATA
pyatsyn-1.0.0.dist-info/WHEEL
pyatsyn-1.0.0.dist-info/entry_points.txt
pyatsyn-1.0.0.dist-info/top_level.txt
pyatsyn-1.0.0.dist-info/RECORD
