Metadata-Version: 2.1
Name: pyatsyn
Version: 1.0.0
Summary: python-based implementation of Analysis-Synthesis-Transformation (ATS) spectral music system
Author-email: "Johnathan G. Lyon" <johnathanglyon@gmail.com>
License: BSD-3-Clause
Project-URL: Homepage, https://github.com/boxofbox/pyatsyn
Project-URL: Bug Tracker, https://github.com/boxofbox/pyatsyn/issues
Project-URL: Documentation, https://pyatsyn.readthedocs.io
Keywords: spectral,audio,dsp,synthesis,music,sound,analysis,ats
Classifier: Programming Language :: Python :: 3
Classifier: Development Status :: 5 - Production/Stable
Classifier: Topic :: Multimedia :: Sound/Audio
Classifier: Topic :: Multimedia :: Sound/Audio :: Analysis
Classifier: Topic :: Multimedia :: Sound/Audio :: Sound Synthesis
Classifier: License :: OSI Approved :: BSD License
Requires-Python: >=3.6
License-File: LICENSE.rst
Requires-Dist: numpy
Requires-Dist: soundfile
Provides-Extra: docs
Requires-Dist: sphinx ; extra == 'docs'
Requires-Dist: sphinx-rtd-theme ; extra == 'docs'
